{"id":"835e7d69-5af2-48eb-8df5-ad4b1fe5d4c8","revision":0,"last_node_id":4,"last_link_id":3,"nodes":[{"id":2,"type":"LoadAudio","pos":[399.5168762207031,-80.17176818847656],"size":[274.080078125,136],"flags":{},"order":0,"mode":0,"inputs":[{"localized_name":"audio","name":"audio","type":"COMBO","widget":{"name":"audio"},"link":null},{"localized_name":"audioUI","name":"audioUI","type":"AUDIO_UI","widget":{"name":"audioUI"},"link":null},{"localized_name":"choose file to upload","name":"upload","type":"AUDIOUPLOAD","widget":{"name":"upload"},"link":null}],"outputs":[{"localized_name":"AUDIO","name":"AUDIO","type":"AUDIO","links":[1]}],"properties":{"Node name for S&R":"LoadAudio"},"widgets_values":["11月19日.WAV",null,""]},{"id":3,"type":"PreviewAudio","pos":[1036.2178955078125,-90.79957580566406],"size":[270,88],"flags":{},"order":2,"mode":0,"inputs":[{"localized_name":"audio","name":"audio","type":"AUDIO","link":2},{"localized_name":"audioUI","name":"audioUI","type":"AUDIO_UI","widget":{"name":"audioUI"},"link":null}],"outputs":[],"properties":{"Node name for S&R":"PreviewAudio"},"widgets_values":[]},{"id":1,"type":"AudioAddWatermark","pos":[701.925048828125,-70.51019287109375],"size":[282.2417907714844,126],"flags":{},"order":1,"mode":0,"inputs":[{"localized_name":"audio","name":"audio","type":"AUDIO","link":1},{"localized_name":"add_watermark","name":"add_watermark","type":"BOOLEAN","widget":{"name":"add_watermark"},"link":null},{"localized_name":"key","name":"key","type":"STRING","widget":{"name":"key"},"link":null},{"localized_name":"unload_model","name":"unload_model","type":"BOOLEAN","widget":{"name":"unload_model"},"link":null}],"outputs":[{"localized_name":"audio","name":"audio","type":"AUDIO","links":[2]},{"localized_name":"watermark","name":"watermark","type":"STRING","links":[3]}],"properties":{"Node name for S&R":"AudioAddWatermark"},"widgets_values":[true,"[212, 211, 146, 56, 201]",true]},{"id":4,"type":"PreviewAny","pos":[1048.7781982421875,64.75254821777344],"size":[216.32684326171875,93.39103698730469],"flags":{},"order":3,"mode":0,"inputs":[{"localized_name":"source","name":"source","type":"*","link":3}],"outputs":[],"properties":{"Node name for S&R":"PreviewAny"},"widgets_values":[]}],"links":[[1,2,0,1,0,"AUDIO"],[2,1,0,3,0,"AUDIO"],[3,1,1,4,0,"*"]],"groups":[],"config":{},"extra":{"ds":{"scale":0.9673108956248864,"offset":[-3.1474940710741057,289.75469710202515]}},"version":0.4}